MANIFEST.in
README.rst
THANKS
setup.py
benchmark/benchmark.py
benchmark/markdown-syntax.md
benchmark/test.py
docs/Makefile
docs/config.yml
docs/assets/elements.less
docs/assets/screen.less
docs/pages/404.html
docs/pages/api.md
docs/pages/changelog.md
docs/pages/development.md
docs/pages/index.md
docs/pages/manual.md
docs/scripts/process_assets.sh
docs/templates/index.html
docs/templates/layout.html
docs/templates/page.html
prat_misaka.egg-info/PKG-INFO
prat_misaka.egg-info/SOURCES.txt
prat_misaka.egg-info/dependency_links.txt
prat_misaka.egg-info/top_level.txt
scripts/misaka
src/.misaka.pyx.swp
src/misaka.c
src/misaka.pyx
src/sundown.pxd
src/wrapper.c
src/wrapper.h
src/wrapper.pxd
src/sundown/.html.c.swp
src/sundown/.html.h.swp
src/sundown/autolink.c
src/sundown/autolink.h
src/sundown/buffer.c
src/sundown/buffer.h
src/sundown/houdini.h
src/sundown/houdini_href_e.c
src/sundown/houdini_html_e.c
src/sundown/html.c
src/sundown/html.h
src/sundown/html_blocks.h
src/sundown/html_smartypants.c
src/sundown/markdown.c
src/sundown/markdown.h
src/sundown/stack.c
src/sundown/stack.h