Metadata-Version: 1.1
Name: prat-misaka
Version: 1.1.5
Summary: Prat fork of Frank Smit's Python binding for Sundown, a markdown parsing library.
Home-page: https://www.github.com/bkad/misaka
Author: Kevin Le
Author-email: solnovus@gmail.com
License: MIT
Platform: UNKNOWN
Classifier: Development Status :: 4 - Beta
Classifier: Intended Audience :: Developers
Classifier: License :: OSI Approved :: MIT License
Classifier: Programming Language :: C
Classifier: Programming Language :: Cython
Classifier: Programming Language :: Python :: 2.7
Classifier: Programming Language :: Python :: 3.2
Classifier: Topic :: Text Processing :: Markup
Classifier: Topic :: Text Processing :: Markup :: HTML
Classifier: Topic :: Utilities
